ballchasing_scrape/__init__.py
ballchasing_scrape/ballchasing_scrape.py
ballchasing_scrape-1.1.8.dist-info/licenses/LICENSE
ballchasing_scrape-1.1.8.dist-info/METADATA
ballchasing_scrape-1.1.8.dist-info/WHEEL
ballchasing_scrape-1.1.8.dist-info/top_level.txt
ballchasing_scrape-1.1.8.dist-info/RECORD
