Metadata-Version: 2.4
Name: ballchasing_scrape
Version: 1.1.8
Summary: A Python Package for scraping information and stats from Rocket League replays hosted on ballchasing.com.
Author-email: Owen Singh <owenbksingh@gmail.com>
Project-URL: Homepage, https://github.com/owensingh38/ballchasing_scrape/
Classifier: Programming Language :: Python :: 3
Classifier: License :: OSI Approved :: MIT License
Classifier: Operating System :: OS Independent
Requires-Python: >=3.8
License-File: LICENSE
Dynamic: license-file
